flop/__init__.py
flop/flop.py
flopp-0.0.1.dist-info/LICENSE
flopp-0.0.1.dist-info/METADATA
flopp-0.0.1.dist-info/WHEEL
flopp-0.0.1.dist-info/top_level.txt
flopp-0.0.1.dist-info/RECORD
