Metadata-Version: 2.1
Name: flopp
Version: 0.0.1
Summary: Produce fully working Flutter projects from existing templates
Home-page: https://github.com/s0m3chill/flop
Author: Dariy Kordiyak
Author-email: d.kordiyak@gmail.com
License: UNKNOWN
Platform: UNKNOWN
Classifier: Programming Language :: Python :: 3
Classifier: License :: OSI Approved :: MIT License
Classifier: Operating System :: OS Independent
Requires-Python: >=3.7
License-File: LICENSE
